pqrs/__init__.py
pqrs/backend.py
pqrs/cli.py
pqrs/config.py
pqrs/paths.py
pqrs/tui.py
pqrs/version.py
pqrs-0.9.0.dist-info/entry_points.txt
pqrs-0.9.0.dist-info/WHEEL
pqrs-0.9.0.dist-info/METADATA
pqrs-0.9.0.dist-info/RECORD
