Metadata-Version: 2.1
Name: pqrs
Version: 0.9.0
Summary: CLI tool to manage Linux workstations.
License: MIT
Author: ProteinQure team
Author-email: team@proteinqure.com
Requires-Python: >=3.8,<4.0
Classifier: License :: OSI Approved :: MIT License
Classifier: Programming Language :: Python :: 3
Classifier: Programming Language :: Python :: 3.10
Classifier: Programming Language :: Python :: 3.8
Classifier: Programming Language :: Python :: 3.9
Requires-Dist: ansible (>=5.2.0,<6.0.0)
Requires-Dist: ansible-runner (>=2.1.1,<3.0.0)
Requires-Dist: datafiles (>=1.1b3,<2.0)
Requires-Dist: plumbum (>=1.7.2,<2.0.0)
Requires-Dist: pq-npyscreen (>=4.9.1,<5.0.0)
Requires-Dist: rich (>=11.0.0,<12.0.0)
Requires-Dist: semantic-version (>=2.8.5,<3.0.0)
Requires-Dist: temppathlib (>=1.1.0,<2.0.0)
Requires-Dist: typer (>=0.4.0,<0.5.0)
